<?xml version="1.0" encoding="UTF-8"?>
<contacts>
  <!-- Página 1 -->
  <contact>
    <name>Bruno Lopes</name>
    <phone>4598166973</phone>
    <page>1</page>
  </contact>

  <!-- Página 2 -->
  <contact>
    <name>Rosa Kozievith</name>
    <phone>4584219317</phone>
    <page>2</page>
  </contact>
  <contact>
    <name>Rozi Kozievith</name>
    <phone>4599373090</phone>
    <page>2</page>
  </contact>
  <contact>
    <name>Janete Profa</name>
    <phone>4598159153</phone>
    <page>2</page>
  </contact>
  <contact>
    <name>Maria Macarrão</name>
    <phone>4591358404</phone>
    <page>2</page>
  </contact>
  <contact>
    <name>Paty BB</name>
    <phone>4598180865</phone>
    <page>2</page>
  </contact>
  <contact>
    <name>Natália Rucco</name>
    <phone>4588292939</phone>
    <page>2</page>
  </contact>
  <contact>
    <name>Rafaela</name>
    <phone>4588151735</phone>
    <page>2</page>
  </contact>
  <contact>
    <name>Tatão</name>
    <phone>4598201468</phone>
    <page>2</page>
  </contact>
  <contact>
    <name>Ana Paula</name>
    <phone>4599367466</phone>
    <page>2</page>
  </contact>
  <contact>
    <name>Luciana</name>
    <phone>4599716816</phone>
    <page>2</page>
  </contact>
  <contact>
    <name>Kelma</name>
    <phone>4599579400</phone>
    <page>2</page>
  </contact>
  <contact>
    <name>Luana</name>
    <phone>4598572980</phone>
    <page>2</page>
  </contact>
  <contact>
    <name>Ana.S</name>
    <phone>4591521694</phone>
    <page>2</page>
  </contact>
  <contact>
    <name>Mara</name>
    <phone>4598180030</phone>
    <page>2</page>
  </contact>
  <contact>
    <name>Clarisse</name>
    <phone>4598173306</phone>
    <page>2</page>
  </contact>
  <contact>
    <name>Carine</name>
    <phone>4599574371</phone>
    <page>2</page>
  </contact>
  <contact>
    <name>Angélika</name>
    <phone>4598158152</phone>
    <page>2</page>
  </contact>
  <contact>
    <name>Angélica B.</name>
    <phone>4588067625</phone>
    <page>2</page>
  </contact>
  <contact>
    <name>Angélica Selo</name>
    <phone>4599697555</phone>
    <page>2</page>
  </contact>
  <contact>
    <name>Beth Selo</name>
    <phone>4599427963</phone>
    <page>2</page>
  </contact>
  <contact>
    <name>Zelinda</name>
    <phone>4599819205</phone>
    <page>2</page>
  </contact>
  <contact>
    <name>Jéssica Reus</name>
    <phone>4598048749</phone>
    <page>2</page>
  </contact>
  <contact>
    <name>Keila</name>
    <phone>4591533554</phone>
    <page>2</page>
  </contact>
  <contact>
    <name>Eliane Lava</name>
    <phone>4591389414</phone>
    <page>2</page>
  </contact>
  <contact>
    <name>Simone Gris</name>
    <phone>4599670282</phone>
    <page>2</page>
  </contact>
  <contact>
    <name>Simoninha</name>
    <phone>4599904710</phone>
    <page>2</page>
  </contact>
  <contact>
    <name>Erika</name>
    <phone>4591590320</phone>
    <page>2</page>
  </contact>
  <contact>
    <name>Idete / Odete</name>
    <phone>4599256468</phone>
    <page>2</page>
  </contact>
  <contact>
    <name>Leila</name>
    <phone>4599424119</phone>
    <page>2</page>
  </contact>
  <contact>
    <name>Lizi</name>
    <phone>4598027771</phone>
    <page>2</page>
  </contact>
  <contact>
    <name>Cida</name>
    <phone>4599281622</phone>
    <page>2</page>
  </contact>

  <!-- Página 3 -->
  <contact>
    <name>Elioni Pastorini</name>
    <phone>4591383823</phone>
    <page>3</page>
  </contact>
  <contact>
    <name>Mary</name>
    <phone>4599000559</phone>
    <page>3</page>
  </contact>
  <contact>
    <name>Mary Lopes</name>
    <phone>4591054501</phone>
    <page>3</page>
  </contact>
  <contact>
    <name>Renata</name>
    <phone>4599278248</phone>
    <page>3</page>
  </contact>
  <contact>
    <name>Jamila</name>
    <phone>4599431955</phone>
    <page>3</page>
  </contact>
  <contact>
    <name>Ere</name>
    <phone>4598551962</phone>
    <page>3</page>
  </contact>
  <contact>
    <name>Thais Barros</name>
    <phone>4599052490</phone>
    <page>3</page>
  </contact>
  <contact>
    <name>Meri</name>
    <phone>4598235988</phone>
    <page>3</page>
  </contact>
  <contact>
    <name>Mara / Ewerton</name>
    <phone>4599969666</phone>
    <page>3</page>
  </contact>
  <contact>
    <name>D. Lídia</name>
    <phone>4598109977</phone>
    <page>3</page>
  </contact>
  <contact>
    <name>Gabriela Custódio</name>
    <phone>4599839330</phone>
    <page>3</page>
  </contact>
  <contact>
    <name>Gabriela Wisch</name>
    <phone>4591228210</phone>
    <page>3</page>
  </contact>
  <contact>
    <name>Giliane</name>
    <phone>4598076959</phone>
    <page>3</page>
  </contact>
  <contact>
    <name>Ellen</name>
    <phone>4591129052</phone>
    <page>3</page>
  </contact>
  <contact>
    <name>Cleusa</name>
    <phone>4591265939</phone>
    <page>3</page>
  </contact>
  <contact>
    <name>Ana Cristina</name>
    <phone>4599566918</phone>
    <page>3</page>
  </contact>
  <contact>
    <name>Ana Luiza</name>
    <phone>4599793750</phone>
    <page>3</page>
  </contact>
  <contact>
    <name>Leonira</name>
    <phone>4599887012</phone>
    <page>3</page>
  </contact>
  <contact>
    <name>Sara / Lara Mariano</name>
    <phone>4599484083</phone>
    <page>3</page>
  </contact>
  <contact>
    <name>Andressa Tavares</name>
    <phone>4598291473</phone>
    <page>3</page>
  </contact>
  <contact>
    <name>Iva Alban</name>
    <phone>4599071046</phone>
    <page>3</page>
  </contact>
  <contact>
    <name>Leidi</name>
    <phone>4598018610</phone>
    <page>3</page>
  </contact>
  <contact>
    <name>Josi Amaral</name>
    <phone>4599045884</phone>
    <page>3</page>
  </contact>
  <contact>
    <name>Josinha</name>
    <phone>4599505129</phone>
    <page>3</page>
  </contact>
  <contact>
    <name>Ivonete</name>
    <phone>4588036353</phone>
    <page>3</page>
  </contact>
  <contact>
    <name>Hosana</name>
    <phone>4599760842</phone>
    <page>3</page>
  </contact>
  <contact>
    <name>Lilian Sthall</name>
    <phone>4591143553</phone>
    <page>3</page>
  </contact>
  <contact>
    <name>Sthefany</name>
    <phone>4599518858</phone>
    <page>3</page>
  </contact>
  <contact>
    <name>Maurícia</name>
    <phone>4599310153</phone>
    <page>3</page>
  </contact>
  <contact>
    <name>Silvana Farmácia</name>
    <phone>4598177547</phone>
    <page>3</page>
  </contact>
  <contact>
    <name>Claúdia</name>
    <phone>4599514412</phone>
    <page>3</page>
  </contact>
  <contact>
    <name>Izabel Mezzomo</name>
    <phone>4591341997</phone>
    <page>3</page>
  </contact>
  <contact>
    <name>Lia Kirsten</name>
    <phone>4599873998</phone>
    <page>3</page>
  </contact>

  <!-- Página 4 -->
  <contact>
    <name>Juliana Paz</name>
    <phone>4598021008</phone>
    <page>4</page>
  </contact>
  <contact>
    <name>Rose Costa</name>
    <phone>4599937809</phone>
    <page>4</page>
  </contact>
  <contact>
    <name>Veraci</name>
    <phone>4599941129</phone>
    <page>4</page>
  </contact>
  <contact>
    <name>Silvani Baseggio (sil)</name>
    <phone>4598450035</phone>
    <page>4</page>
  </contact>
  <contact>
    <name>Antônia</name>
    <phone>4598521380</phone>
    <page>4</page>
  </contact>
  <contact>
    <name>Jéssica</name>
    <phone>4598188047</phone>
    <page>4</page>
  </contact>
  <contact>
    <name>Faby</name>
    <phone>4591351202</phone>
    <page>4</page>
  </contact>
  <contact>
    <name>Laurita</name>
    <phone>4599797731</phone>
    <page>4</page>
  </contact>
  <contact>
    <name>Rose Vizinha</name>
    <phone>4599433244</phone>
    <page>4</page>
  </contact>
  <contact>
    <name>Rose Vieira</name>
    <phone>4599196434</phone>
    <page>4</page>
  </contact>
  <contact>
    <name>Maria Eduarda - Vanina</name>
    <phone>4591083470</phone>
    <page>4</page>
  </contact>
  <contact>
    <name>Fernanda Bueno</name>
    <phone>4598046260</phone>
    <page>4</page>
  </contact>
  <contact>
    <name>Tai</name>
    <phone>4598327679</phone>
    <page>4</page>
  </contact>
  <contact>
    <name>Sinara</name>
    <phone>4598041705</phone>
    <page>4</page>
  </contact>
  <contact>
    <name>Vanessa Bonatto</name>
    <phone>4588116378</phone>
    <page>4</page>
  </contact>
  <contact>
    <name>Neuza</name>
    <phone>4591538876</phone>
    <page>4</page>
  </contact>
  <contact>
    <name>Nilda Miguel</name>
    <phone>4599835001</phone>
    <page>4</page>
  </contact>
  <contact>
    <name>Poliana</name>
    <phone>4599235690</phone>
    <page>4</page>
  </contact>
  <contact>
    <name>Dani (menino)</name>
    <phone>4599120698</phone>
    <page>4</page>
  </contact>
  <contact>
    <name>Isaura (Sheila grego)</name>
    <phone>6993899080</phone>
    <page>4</page>
  </contact>
  <contact>
    <name>Andreia Nandi</name>
    <phone>4599294644</phone>
    <page>4</page>
  </contact>
  <contact>
    <name>Inês</name>
    <phone>4598251741</phone>
    <page>4</page>
  </contact>
  <contact>
    <name>Sol</name>
    <phone>4584050818</phone>
    <page>4</page>
  </contact>
  <contact>
    <name>Zelinda</name>
    <phone>4599819205</phone>
    <page>4</page>
  </contact>
  <contact>
    <name>Paula</name>
    <phone>4598449683</phone>
    <page>4</page>
  </contact>
  <contact>
    <name>Eve</name>
    <phone>4599191317</phone>
    <page>4</page>
  </contact>

  <!-- Página 5 -->
  <contact>
    <name>Rose Gomes</name>
    <phone>4599835764</phone>
    <page>5</page>
  </contact>
  <contact>
    <name>Jéssica Gomes</name>
    <phone>4599525880</phone>
    <page>5</page>
  </contact>
  <contact>
    <name>Evanir</name>
    <phone>4588048887</phone>
    <page>5</page>
  </contact>
  <contact>
    <name>Nadir Reis</name>
    <phone>4187385534</phone>
    <page>5</page>
  </contact>
  <contact>
    <name>Maria Roma</name>
    <phone>4599050636</phone>
    <page>5</page>
  </contact>
  <contact>
    <name>Jaque Rucco</name>
    <phone>4599778637</phone>
    <page>5</page>
  </contact>
  <contact>
    <name>Mayara</name>
    <phone>45988083974</phone>
    <page>5</page>
  </contact>
  <contact>
    <name>Marileine</name>
    <phone>4599407210</phone>
    <page>5</page>
  </contact>
  <contact>
    <name>Marilene Onório</name>
    <phone>4598418705</phone>
    <page>5</page>
  </contact>
  <contact>
    <name>Grazi</name>
    <phone>4598105299</phone>
    <page>5</page>
  </contact>
  <contact>
    <name>Luiza Lorena</name>
    <phone>4599930581</phone>
    <page>5</page>
  </contact>
  <contact>
    <name>Silvia Renata Rigue</name>
    <phone>4591247800</phone>
    <page>5</page>
  </contact>
  <contact>
    <name>Tiffany</name>
    <phone>4599978564</phone>
    <page>5</page>
  </contact>
  <contact>
    <name>Dielsa</name>
    <phone>4591189407</phone>
    <page>5</page>
  </contact>
  <contact>
    <name>Cris Sente</name>
    <phone>4598594817</phone>
    <page>5</page>
  </contact>
  <contact>
    <name>Susete</name>
    <phone>4599269660</phone>
    <page>5</page>
  </contact>
  <contact>
    <name>Letícia Locatelli</name>
    <phone>4598200710</phone>
    <page>5</page>
  </contact>
  <contact>
    <name>Jaysa</name>
    <phone>4591213089</phone>
    <page>5</page>
  </contact>
  <contact>
    <name>Vivi Xeque</name>
    <phone>4591330796</phone>
    <page>5</page>
  </contact>
  <contact>
    <name>Olga</name>
    <phone>4598103875</phone>
    <page>5</page>
  </contact>
  <contact>
    <name>Suzana</name>
    <phone>4591225595</phone>
    <page>5</page>
  </contact>
  <contact>
    <name>Eva</name>
    <phone>4599514946</phone>
    <page>5</page>
  </contact>
  <contact>
    <name>Regiane</name>
    <phone>4591400343</phone>
    <page>5</page>
  </contact>
  <contact>
    <name>Gabizinha</name>
    <phone>4591463891</phone>
    <page>5</page>
  </contact>
  <contact>
    <name>Nami</name>
    <phone>4599078399</phone>
    <page>5</page>
  </contact>
  <contact>
    <name>Luana</name>
    <phone>4598572980</phone>
    <page>5</page>
  </contact>
  <contact>
    <name>Michele Oliveira</name>
    <phone>4591542158</phone>
    <page>5</page>
  </contact>
  <contact>
    <name>Crislaine</name>
    <phone>4599157205</phone>
    <page>5</page>
  </contact>
  <contact>
    <name>Lúcia</name>
    <phone>4599544651</phone>
    <page>5</page>
  </contact>
  <contact>
    <name>Silvana Ramão</name>
    <phone>4599375903</phone>
    <page>5</page>
  </contact>
  <contact>
    <name>Amanda Chácara</name>
    <phone>4599225256</phone>
    <page>5</page>
  </contact>
</contacts>
